openai_usage_logger/__init__.py
openai_usage_logger/openai_usage_logger.py
openai_usage_logger-0.1.2.dist-info/LICENSE.md
openai_usage_logger-0.1.2.dist-info/METADATA
openai_usage_logger-0.1.2.dist-info/WHEEL
openai_usage_logger-0.1.2.dist-info/top_level.txt
openai_usage_logger-0.1.2.dist-info/RECORD
