Metadata-Version: 2.1
Name: openai_usage_logger
Version: 0.1.2
Summary: A utility for logging OpenAI API usage and costs.
Author-email: Tal Darom <tal.darom@gmail.com>
License: MIT License
Project-URL: Bug Tracker, https://github.com/talda/openai-usage-logger/issues
Classifier: Development Status :: 3 - Alpha
Classifier: Intended Audience :: Developers
Classifier: License :: OSI Approved :: MIT License
Classifier: Programming Language :: Python :: 3
License-File: LICENSE.md
